setup.py
makina/__init__.py
makina.recipe.postgres.egg-info/PKG-INFO
makina.recipe.postgres.egg-info/SOURCES.txt
makina.recipe.postgres.egg-info/dependency_links.txt
makina.recipe.postgres.egg-info/entry_points.txt
makina.recipe.postgres.egg-info/namespace_packages.txt
makina.recipe.postgres.egg-info/not-zip-safe
makina.recipe.postgres.egg-info/requires.txt
makina.recipe.postgres.egg-info/top_level.txt
makina/recipe/__init__.py
makina/recipe/postgres/README.txt
makina/recipe/postgres/__init__.py
makina/recipe/postgres/docs/README.txt
makina/recipe/postgres/doctests/README.txt
makina/recipe/postgres/tests/__init__.py
makina/recipe/postgres/tests/test_postgresdocs.py