Metadata-Version: 1.0
Name: makina.recipe.postgres
Version: 0.1
Summary: init a postgresql's database for the project
Home-page: http://www.makina-corpus.org
Author: jeanmichel FRANCOIS
Author-email: jeanmichel.francois@makina-corpus.com
License: GPL
Platform: UNKNOWN
Classifier: Programming Language :: Python
Classifier: Topic :: Software Development :: Libraries :: Python Modules
